docs/conf.py
examples/__init__.py
examples/approx_metrics/__init__.py
examples/approx_metrics/main.py
examples/approx_metrics/main_test.py
examples/flax_integration/__init__.py
examples/flax_integration/main.py
examples/flax_integration/main_test.py
examples/segmentation/__init__.py
examples/segmentation/main.py
examples/segmentation/main_test.py
examples/t5x/models.py
examples/t5x/models_test.py
examples/t5x/tasks.py
examples/t5x/tasks_test.py
rax/__init__.py
rax/types.py
rax/utils.py
rax/_src/__init__.py
rax/_src/lambdaweights.py
rax/_src/lambdaweights_test.py
rax/_src/losses.py
rax/_src/losses_test.py
rax/_src/metrics.py
rax/_src/metrics_test.py
rax/_src/segment_utils.py
rax/_src/segment_utils_test.py
rax/_src/t12n.py
rax/_src/t12n_test.py
rax/_src/types.py
rax/_src/utils.py
rax/_src/utils_test.py
rax-0.3.0.dist-info/LICENSE
rax-0.3.0.dist-info/METADATA
rax-0.3.0.dist-info/WHEEL
rax-0.3.0.dist-info/top_level.txt
rax-0.3.0.dist-info/RECORD
