Metadata-Version: 2.1
Name: rax
Version: 0.3.0
Summary: Learning-to-Rank using JAX.
Home-page: https://github.com/google/rax
Author: Google
Author-email: rax-dev@google.com
License: Apache 2.0
Keywords: learning-to-rank jax ranking
Classifier: Development Status :: 4 - Beta
Classifier: Intended Audience :: Science/Research
Classifier: Intended Audience :: Developers
Classifier: License :: OSI Approved :: Apache Software License
Classifier: Operating System :: OS Independent
Classifier: Programming Language :: Python :: 3
Classifier: Topic :: Scientific/Engineering :: Artificial Intelligence
Classifier: Topic :: Software Development :: Libraries :: Python Modules
Requires-Python: >=3.8
License-File: LICENSE
Requires-Dist: jax (>=0.2.0)
Requires-Dist: jaxlib (>=0.1.0)
Requires-Dist: typing-extensions (>=3.7.0)
